{
  "meta": {
    "note": "International comparison using World Bank, IMF, ADB, and WHO data. Most recent available year shown.",
    "dataUpdatedAt": "2026-05-13T02:33:45.232Z"
  },
  "charts": [
    {
      "title": "Stunting prevalence",
      "unit": "% under 5",
      "source": "WHO Global Health Observatory",
      "countries": [
        {
          "code": "VNM",
          "name": "Vietnam",
          "value": 17.9,
          "year": 2024
        },
        {
          "code": "LKA",
          "name": "Sri Lanka",
          "value": 10.1,
          "year": 2024
        },
        {
          "code": "IDN",
          "name": "Indonesia",
          "value": 21.2,
          "year": 2024
        },
        {
          "code": "BGD",
          "name": "Bangladesh",
          "value": 24.4,
          "year": 2024
        },
        {
          "code": "THA",
          "name": "Thailand",
          "value": 13.1,
          "year": 2024
        },
        {
          "code": "IND",
          "name": "India",
          "value": 31.8,
          "year": 2024
        },
        {
          "code": "JPN",
          "name": "Japan",
          "value": 4.5,
          "year": 2024
        },
        {
          "code": "CHN",
          "name": "China",
          "value": 4.5,
          "year": 2024
        },
        {
          "code": "USA",
          "name": "United States",
          "value": 4.7,
          "year": 2024
        },
        {
          "code": "PAK",
          "name": "Pakistan",
          "value": 32.6,
          "year": 2024
        },
        {
          "code": "KOR",
          "name": "Korea",
          "value": 1.8,
          "year": 2024
        }
      ]
    },
    {
      "title": "Under-5 mortality rate",
      "unit": "per 1,000",
      "source": "WHO Global Health Observatory",
      "countries": [
        {
          "code": "CHN",
          "name": "China",
          "value": 16.25,
          "year": 2023
        },
        {
          "code": "VNM",
          "name": "Vietnam",
          "value": 47.61,
          "year": 2023
        },
        {
          "code": "USA",
          "name": "United States",
          "value": 16.63,
          "year": 2023
        },
        {
          "code": "KOR",
          "name": "Korea",
          "value": 3.79,
          "year": 2023
        },
        {
          "code": "BGD",
          "name": "Bangladesh",
          "value": 115.11,
          "year": 2023
        },
        {
          "code": "THA",
          "name": "Thailand",
          "value": 34.45,
          "year": 2023
        },
        {
          "code": "LKA",
          "name": "Sri Lanka",
          "value": 18.32,
          "year": 2023
        },
        {
          "code": "IND",
          "name": "India",
          "value": 80.48,
          "year": 2023
        },
        {
          "code": "IDN",
          "name": "Indonesia",
          "value": 140.5,
          "year": 2023
        },
        {
          "code": "JPN",
          "name": "Japan",
          "value": 3.08,
          "year": 2023
        },
        {
          "code": "PAK",
          "name": "Pakistan",
          "value": 155.03,
          "year": 2023
        }
      ]
    },
    {
      "title": "Wasting prevalence",
      "unit": "% under 5",
      "source": "World Bank Open Data",
      "countries": [
        {
          "code": "BGD",
          "name": "Bangladesh",
          "value": 10.7,
          "year": 2022
        },
        {
          "code": "IDN",
          "name": "Indonesia",
          "value": 8.4,
          "year": 2023
        },
        {
          "code": "IND",
          "name": "India",
          "value": 18.7,
          "year": 2020
        },
        {
          "code": "KOR",
          "name": "Korea",
          "value": 0.2,
          "year": 2020
        },
        {
          "code": "LKA",
          "name": "Sri Lanka",
          "value": 9.3,
          "year": 2024
        },
        {
          "code": "THA",
          "name": "Thailand",
          "value": 7.2,
          "year": 2022
        },
        {
          "code": "USA",
          "name": "United States",
          "value": 0.1,
          "year": 2022
        },
        {
          "code": "VNM",
          "name": "Vietnam",
          "value": 4.4,
          "year": 2023
        }
      ]
    }
  ]
}